ariadne_ai/__init__.py
ariadne_ai/evaluators/__init__.py
ariadne_ai/evaluators/rag/__init__.py
ariadne_ai/evaluators/rag/answer_relevance_evaluator.py
ariadne_ai/evaluators/rag/context_relevance_evaluator.py
ariadne_ai/evaluators/rag/faithfulness_evaluator.py
ariadne_ai/evaluators/rag/rag_evaluator.py
ariadne_ai/evaluators/text_summarization/__init__.py
ariadne_ai/evaluators/text_summarization/hallucination_evaluator.py
ariadne_ai/evaluators/text_summarization/informativeness_evaluator.py
ariadne_ai/evaluators/text_summarization/summarization_evaluator.py
ariadne_ai/llms/__init__.py
ariadne_ai/llms/base_llm_evaluator.py
ariadne_ai/llms/open_ai_completion.py
ariadne_ai/llms/rag/__init__.py
ariadne_ai/llms/rag/answer_relevance.py
ariadne_ai/llms/rag/context_relevance.py
ariadne_ai/llms/rag/faithfulness.py
ariadne_ai/llms/text_summarization/__init__.py
ariadne_ai/llms/text_summarization/question_answerer.py
ariadne_ai/llms/text_summarization/question_generator.py
ariadne_ai/loaders/__init__.py
ariadne_ai/loaders/loader.py
ariadne_ai/loaders/rag_loader.py
ariadne_ai/loaders/summarization_loader.py
ariadne_ai/metrics/__init__.py
ariadne_ai/metrics/metric.py
ariadne_ai/metrics/rag/__init__.py
ariadne_ai/metrics/rag/answer_relevance_failure.py
ariadne_ai/metrics/rag/context_relevance_failure.py
ariadne_ai/metrics/rag/faithfulness_failure.py
ariadne_ai/metrics/text_summarization/__init__.py
ariadne_ai/metrics/text_summarization/aggreement_score.py
ariadne_ai/metrics/text_summarization/contradiction_failure.py
ariadne_ai/metrics/text_summarization/hallucination_failure.py
ariadne_ai/metrics/text_summarization/informativeness_failure.py
ariadne_ai/publishers/__init__.py
ariadne_ai/publishers/publisher.py
ariadne_ai/publishers/publisher_log.py
ariadne_ai-0.1.12.dist-info/LICENSE
ariadne_ai-0.1.12.dist-info/METADATA
ariadne_ai-0.1.12.dist-info/WHEEL
ariadne_ai-0.1.12.dist-info/RECORD
