Metadata-Version: 2.1
Name: ariadne-ai
Version: 0.1.12
Summary: 
Author: Shiv
Author-email: shiv@athina.ai
Requires-Python: >=3.9,<4.0
Classifier: Programming Language :: Python :: 3
Classifier: Programming Language :: Python :: 3.9
Classifier: Programming Language :: Python :: 3.10
Classifier: Programming Language :: Python :: 3.11
Requires-Dist: athina-logger (>=0.0.11,<0.0.12)
Requires-Dist: datasets (>=2.14.5,<3.0.0)
Requires-Dist: openai (>=0.28.0,<0.29.0)
Requires-Dist: pandas (>=2.1.0,<3.0.0)
Requires-Dist: python-dotenv (>=1.0.0,<2.0.0)
Requires-Dist: scikit-learn (>=1.3.0,<2.0.0)
